cloudshell/__init__.py
cloudshell/traffic/__init__.py
cloudshell/traffic/helpers.py
cloudshell/traffic/rest_api_helpers.py
cloudshell/traffic/tg.py
cloudshell_traffic-3.4.3.dist-info/License.txt
cloudshell_traffic-3.4.3.dist-info/METADATA
cloudshell_traffic-3.4.3.dist-info/WHEEL
cloudshell_traffic-3.4.3.dist-info/top_level.txt
cloudshell_traffic-3.4.3.dist-info/RECORD
