Metadata-Version: 2.1
Name: cloudshell-traffic
Version: 3.4.3
Summary: Cloudshell sub-package for traffic generators shells - chassis and controllers
Home-page: https://github.com/QualiSystems/cloudshell-traffic
Author: QualiSystems
Author-email: info@qualisystems.com
License: Apache Software License
Classifier: Development Status :: 5 - Production/Stable
Classifier: Natural Language :: English
Classifier: License :: OSI Approved :: Apache Software License
Classifier: Intended Audience :: Developers
Classifier: Operating System :: OS Independent
Classifier: Topic :: Software Development :: Testing
Classifier: Programming Language :: Python :: 3.7
Classifier: Programming Language :: Python :: 3.9
License-File: License.txt
Requires-Dist: requests
Requires-Dist: cloudshell-logging (==1.0.3)
Requires-Dist: cloudshell-orch-core (<3.4.0.0,>=3.3.0.0)
Requires-Dist: cloudshell-shell-core (<6.0.0,>=5.0.3)
